ibis/__init__.py
ibis/filter.py
ibis/kosh_operators.py
ibis/likelihoods.py
ibis/mcmc.py
ibis/mcmc_diagnostics.py
ibis/pce_model.py
ibis/plots.py
ibis/sensitivity.py
llnl_ibis-1.2.0.dist-info/METADATA
llnl_ibis-1.2.0.dist-info/WHEEL
llnl_ibis-1.2.0.dist-info/entry_points.txt
llnl_ibis-1.2.0.dist-info/licenses/LICENSE
llnl_ibis-1.2.0.dist-info/licenses/NOTICE
llnl_ibis-1.2.0.dist-info/RECORD
