Metadata-Version: 2.4
Name: llnl-ibis
Version: 1.2.0
Summary: A tool to facilitate uncertainity quantification and sensitivity methods.
License: BSD 3-Clause License
License-File: LICENSE
License-File: NOTICE
Author: Andrew Fillmore
Author-email: fillmore1@llnl.gov
Maintainer: Renee Olson
Maintainer-email: olson59@llnl.gov
Requires-Python: >=3.6
Classifier: Development Status :: 5 - Production/Stable
Classifier: Intended Audience :: Developers
Classifier: Intended Audience :: Education
Classifier: Intended Audience :: Science/Research
Classifier: License :: Other/Proprietary License
Classifier: Operating System :: OS Independent
Classifier: Programming Language :: Python :: 3
Classifier: Programming Language :: Python :: 3.6
Classifier: Programming Language :: Python :: 3.7
Classifier: Programming Language :: Python :: 3.8
Classifier: Programming Language :: Python :: 3.9
Classifier: Programming Language :: Python :: 3.10
Classifier: Programming Language :: Python :: 3.11
Classifier: Programming Language :: Python :: 3.12
Classifier: Programming Language :: Python :: 3.13
Classifier: Programming Language :: Python :: 3.14
Classifier: Topic :: Scientific/Engineering
Classifier: Topic :: Scientific/Engineering :: Mathematics
Requires-Dist: kosh
Requires-Dist: matplotlib
Requires-Dist: networkx
Requires-Dist: numpy
Requires-Dist: scikit-learn
Requires-Dist: scipy
Requires-Dist: trata
Project-URL: Bug Tracker, https://github.com/LLNL/ibis/issues
Project-URL: Documentation, https://ibis.readthedocs.io/
Project-URL: Discussions, https://github.com/LLNL/ibis/discussions
Project-URL: Homepage, https://github.com/llnl/ibis
